hdlworkflow/__init__.py
hdlworkflow/gtkwave.py
hdlworkflow/hdlworkflow.py
hdlworkflow/logging.py
hdlworkflow/nvc.py
hdlworkflow/riviera.py
hdlworkflow/surfer.py
hdlworkflow/utils.py
hdlworkflow/vivado.py
hdlworkflow-0.4.1.dist-info/licenses/LICENSE
hdlworkflow-0.4.1.dist-info/METADATA
hdlworkflow-0.4.1.dist-info/WHEEL
hdlworkflow-0.4.1.dist-info/entry_points.txt
hdlworkflow-0.4.1.dist-info/top_level.txt
hdlworkflow-0.4.1.dist-info/RECORD
