Metadata-Version: 2.4
Name: hdlworkflow
Version: 0.4.1
Summary: Seamless FPGA workflows.
Author-email: Scott Huynh <scott.s.huynh@gmail.com>
Keywords: fpga,vhdl,hdl,cli,simulation,synthesis,workflow
Classifier: Programming Language :: Python :: 3.10
Classifier: Operating System :: OS Independent
Classifier: Topic :: Scientific/Engineering :: Electronic Design Automation (EDA)
Requires-Python: >=3.10
License-File: LICENSE
Dynamic: license-file
